{
    "usage_classifier": {
        "best_model": "RandomForest",
        "f1_score": 0.3654,
        "accuracy": 0.365
    },
    "mental_health_clf": {
        "best_model": "GradientBoosting",
        "f1_score": 0.9071,
        "accuracy": 0.9072
    },
    "productivity_reg": {
        "best_model": "Ridge+GridSearch",
        "r2": 0.6888,
        "rmse": 2.1
    },
    "user_segmentation": {
        "k": 5,
        "silhouette": 0.2185,
        "personas": {
            "1": "Night Scroller",
            "0": "Weekend Binger",
            "4": "Balanced Professional",
            "2": "Productive Learner",
            "3": "Social Addict"
        }
    }
}